LICENSE
README.md
setup.py
AntFake.egg-info/PKG-INFO
AntFake.egg-info/SOURCES.txt
AntFake.egg-info/dependency_links.txt
AntFake.egg-info/requires.txt
AntFake.egg-info/top_level.txt
antFake/__init__.py
antFake/ant_fake.py