Metadata-Version: 2.1
Name: AntFake
Version: 0.1.5
Summary: Ant is library for generation random string, float, eth address and pk, etc
Home-page: https://github.com/inkviz96/antFake
Author: Inkviz96
Author-email: b-semen-b@mail.ru
License: MIT
Keywords: fake test web3 eth
Platform: UNKNOWN
Classifier: Programming Language :: Python :: 3.8
Classifier: License :: OSI Approved :: GNU General Public License v3 (GPLv3)
License-File: LICENSE
